[
  {
    "vehicle_id": "VH-0001",
    "vehicle_type": "large_trailer",
    "capacity_weight": 14816.2,
    "capacity_volume": 52.0,
    "operating_cost": 17185.0
  },
  {
    "vehicle_id": "VH-0002",
    "vehicle_type": "large_trailer",
    "capacity_weight": 15515.3,
    "capacity_volume": 48.6,
    "operating_cost": 15517.9
  },
  {
    "vehicle_id": "VH-0003",
    "vehicle_type": "medium_truck",
    "capacity_weight": 6848.5,
    "capacity_volume": 26.8,
    "operating_cost": 8369.2
  },
  {
    "vehicle_id": "VH-0004",
    "vehicle_type": "large_trailer",
    "capacity_weight": 16215.9,
    "capacity_volume": 53.1,
    "operating_cost": 15855.6
  },
  {
    "vehicle_id": "VH-0005",
    "vehicle_type": "medium_truck",
    "capacity_weight": 6757.6,
    "capacity_volume": 25.3,
    "operating_cost": 8376.3
  },
  {
    "vehicle_id": "VH-0006",
    "vehicle_type": "medium_truck",
    "capacity_weight": 6624.7,
    "capacity_volume": 25.2,
    "operating_cost": 8275.5
  },
  {
    "vehicle_id": "VH-0007",
    "vehicle_type": "large_trailer",
    "capacity_weight": 14138.3,
    "capacity_volume": 53.4,
    "operating_cost": 16706.6
  },
  {
    "vehicle_id": "VH-0008",
    "vehicle_type": "large_trailer",
    "capacity_weight": 15229.9,
    "capacity_volume": 52.3,
    "operating_cost": 13511.2
  },
  {
    "vehicle_id": "VH-0009",
    "vehicle_type": "large_trailer",
    "capacity_weight": 14734.7,
    "capacity_volume": 50.9,
    "operating_cost": 14785.0
  },
  {
    "vehicle_id": "VH-0010",
    "vehicle_type": "small_tempo",
    "capacity_weight": 2120.5,
    "capacity_volume": 8.7,
    "operating_cost": 3174.8
  }
]